dicom_mask/__init__.py
dicom_mask/convert.py
dicom_mask-0.0.9.dist-info/LICENSE
dicom_mask-0.0.9.dist-info/METADATA
dicom_mask-0.0.9.dist-info/WHEEL
dicom_mask-0.0.9.dist-info/top_level.txt
dicom_mask-0.0.9.dist-info/RECORD
