Metadata-Version: 2.1
Name: dicom-mask
Version: 0.0.9
Summary: Export structure from dicom to numpy binary mask
Home-page: https://github.com/Abe404/dicom_mask
Author: Abraham George Smith
Author-email: abe@abesmith.co.uk
License: UNKNOWN
Project-URL: Bug Tracker, https://github.com/Abe404/dicom_mask/issues
Platform: UNKNOWN
Classifier: Programming Language :: Python :: 3
Classifier: License :: OSI Approved :: BSD License
Classifier: Operating System :: OS Independent
Requires-Python: >=3.6
License-File: LICENSE
